pubmed_paper_fetcher/__init__.py
pubmed_paper_fetcher/cli.py
pubmed_paper_fetcher/fetcher.py
pubmed_paper_fetcher_supri267-0.1.1.dist-info/entry_points.txt
pubmed_paper_fetcher_supri267-0.1.1.dist-info/METADATA
pubmed_paper_fetcher_supri267-0.1.1.dist-info/WHEEL
pubmed_paper_fetcher_supri267-0.1.1.dist-info/RECORD
