Metadata-Version: 2.3
Name: pubmed-paper-fetcher-supri267
Version: 0.1.1
Summary: A Python program to fetch research papers from PubMed with non-academic authors affiliated with pharmaceutical or biotech companies.
License: MIT
Author: Supriya
Author-email: akkalasupriya3@gmail.com
Requires-Python: >=3.8
Classifier: License :: OSI Approved :: MIT License
Classifier: Programming Language :: Python :: 3
Classifier: Programming Language :: Python :: 3.8
Classifier: Programming Language :: Python :: 3.9
Classifier: Programming Language :: Python :: 3.10
Classifier: Programming Language :: Python :: 3.11
Classifier: Programming Language :: Python :: 3.12
Classifier: Programming Language :: Python :: 3.13
Requires-Dist: requests (>=2.32.3,<3.0.0)
